tensorboard_data_server/__init__.py
tensorboard_data_server-0.5.0.dist-info/METADATA
tensorboard_data_server-0.5.0.dist-info/WHEEL
tensorboard_data_server-0.5.0.dist-info/top_level.txt
tensorboard_data_server-0.5.0.dist-info/RECORD
