Metadata-Version: 2.1
Name: tensorboard-data-server
Version: 0.5.0
Summary: Fast data loading for TensorBoard
Home-page: https://github.com/tensorflow/tensorboard/tree/master/tensorboard/data/server
Author: Google Inc.
Author-email: packages@tensorflow.org
License: Apache 2.0
Keywords: tensorflow tensorboard tensor machine learning visualizer
Platform: UNKNOWN
Classifier: Development Status :: 2 - Pre-Alpha
Classifier: Intended Audience :: Developers
Classifier: Intended Audience :: Education
Classifier: Intended Audience :: Science/Research
Classifier: License :: OSI Approved :: Apache Software License
Classifier: Programming Language :: Python :: 3
Classifier: Programming Language :: Python :: 3.6
Classifier: Programming Language :: Python :: 3.7
Classifier: Programming Language :: Python :: 3.8
Classifier: Programming Language :: Rust
Classifier: Topic :: Scientific/Engineering :: Mathematics
Classifier: Topic :: Software Development :: Libraries :: Python Modules
Classifier: Topic :: Software Development :: Libraries
Requires-Python: >=3.6
